docs/conf.py
docs/test_only.py
docs/_build/html/_downloads/85080fe3721f5e62197ad5987551979d/plot_custom_semi_continuous.py
docs/_build/html/_downloads/a4acde65da701e6eefbcc88e19c8eb9d/plot_goes_gpm.py
docs/_build/html/_downloads/cd921992fea749a1ec0476a69b96ec55/plot_radar_ppi.py
docs/_build/html/_downloads/f02740ff5c1c4140a231e4fdf0f94f52/plot_continuous_topo.py
docs/_extensions/patch_gallery_images.py
docs/auto_examples/plot_continuous_topo.py
docs/auto_examples/plot_custom_semi_continuous.py
docs/auto_examples/plot_goes_gpm.py
docs/auto_examples/plot_radar_ppi.py
domutils/__init__.py
domutils/_py_tools.py
domutils/geo_tools/__init__.py
domutils/geo_tools/_find_nearest.py
domutils/geo_tools/lat_lon_extend.py
domutils/geo_tools/lat_lon_range_az.py
domutils/geo_tools/lat_lon_to_xyz.py
domutils/geo_tools/projinds.py
domutils/geo_tools/rotation_matrix.py
domutils/geo_tools/tests/__init__.py
domutils/geo_tools/tests/test_geo_tools.py
domutils/legs/__init__.py
domutils/legs/legs.py
domutils/legs/cb/__init__.py
domutils/legs/cb/cb_noshow.py
domutils/legs/col_map_fct/__init__.py
domutils/legs/col_map_fct/exact_open_end.py
domutils/legs/col_map_fct/extend_open_end.py
domutils/legs/col_map_fct/lin_map.py
domutils/legs/col_map_fct/solid_map.py
domutils/legs/col_map_fct/tests/__init__.py
domutils/legs/col_map_fct/tests/test_col_map_fct.py
domutils/legs/col_utils/__init__.py
domutils/legs/col_utils/col_pair.py
domutils/legs/col_utils/col_rgb.py
domutils/legs/col_utils/tests/__init__.py
domutils/legs/col_utils/tests/test_col_utils.py
domutils/legs/tests/__init__.py
domutils/legs/tests/test_legs.py
domutils/legs/tests/test_legs_tutorial.py
domutils/legs/validation_tools/__init__.py
domutils/legs/validation_tools/color_arr_and_solid.py
domutils/legs/validation_tools/continuity_of_mapping.py
domutils/legs/validation_tools/dark_pos.py
domutils/legs/validation_tools/exceptions.py
domutils/legs/validation_tools/input_data.py
domutils/legs/validation_tools/map_f_arr.py
domutils-2.3.1.dist-info/licenses/LICENSE
domutils-2.3.1.dist-info/METADATA
domutils-2.3.1.dist-info/WHEEL
domutils-2.3.1.dist-info/top_level.txt
domutils-2.3.1.dist-info/RECORD
